Compiled from "RedisVectorStore.java"
public class org.springframework.ai.vectorstore.redis.RedisVectorStore extends org.springframework.ai.vectorstore.observation.AbstractObservationVectorStore implements org.springframework.beans.factory.InitializingBean {
  public static final java.lang.String DEFAULT_INDEX_NAME;

  public static final java.lang.String DEFAULT_CONTENT_FIELD_NAME;

  public static final java.lang.String DEFAULT_EMBEDDING_FIELD_NAME;

  public static final java.lang.String DEFAULT_PREFIX;

  public static final org.springframework.ai.vectorstore.redis.RedisVectorStore$Algorithm DEFAULT_VECTOR_ALGORITHM;

  public static final java.lang.String DISTANCE_FIELD_NAME;

  private static final java.lang.String QUERY_FORMAT;

  private static final redis.clients.jedis.json.Path2 JSON_SET_PATH;

  private static final java.lang.String JSON_PATH_PREFIX;

  private static final org.slf4j.Logger logger;

  private static final java.util.function.Predicate<java.lang.Object> RESPONSE_OK;

  private static final java.util.function.Predicate<java.lang.Object> RESPONSE_DEL_OK;

  private static final java.lang.String VECTOR_TYPE_FLOAT32;

  private static final java.lang.String EMBEDDING_PARAM_NAME;

  private static final java.lang.String DEFAULT_DISTANCE_METRIC;

  private final redis.clients.jedis.JedisPooled jedis;

  private final boolean initializeSchema;

  private final java.lang.String indexName;

  private final java.lang.String prefix;

  private final java.lang.String contentFieldName;

  private final java.lang.String embeddingFieldName;

  private final org.springframework.ai.vectorstore.redis.RedisVectorStore$Algorithm vectorAlgorithm;

  private final java.util.List<org.springframework.ai.vectorstore.redis.RedisVectorStore$MetadataField> metadataFields;

  private final org.springframework.ai.vectorstore.filter.FilterExpressionConverter filterExpressionConverter;

  protected org.springframework.ai.vectorstore.redis.RedisVectorStore(org.springframework.ai.vectorstore.redis.RedisVectorStore$Builder);
    Code:
       0: aload_0
       1: aload_1
       2: invokespecial #1                  // Method org/springframework/ai/vectorstore/observation/AbstractObservationVectorStore."<init>":(Lorg/springframework/ai/vectorstore/AbstractVectorStoreBuilder;)V
       5: aload_1
       6: getfield      #7                  // Field org/springframework/ai/vectorstore/redis/RedisVectorStore$Builder.jedis:Lredis/clients/jedis/JedisPooled;
       9: ldc           #13                 // String JedisPooled must not be null
      11: invokestatic  #15                 // Method org/springframework/util/Assert.notNull:(Ljava/lang/Object;Ljava/lang/String;)V
      14: aload_0
      15: aload_1
      16: getfield      #7                  // Field org/springframework/ai/vectorstore/redis/RedisVectorStore$Builder.jedis:Lredis/clients/jedis/JedisPooled;
      19: putfield      #21                 // Field jedis:Lredis/clients/jedis/JedisPooled;
      22: aload_0
      23: aload_1
      24: getfield      #24                 // Field org/springframework/ai/vectorstore/redis/RedisVectorStore$Builder.indexName:Ljava/lang/String;
      27: putfield      #28                 // Field indexName:Ljava/lang/String;
      30: aload_0
      31: aload_1
      32: getfield      #29                 // Field org/springframework/ai/vectorstore/redis/RedisVectorStore$Builder.prefix:Ljava/lang/String;
      35: putfield      #32                 // Field prefix:Ljava/lang/String;
      38: aload_0
      39: aload_1
      40: getfield      #33                 // Field org/springframework/ai/vectorstore/redis/RedisVectorStore$Builder.contentFieldName:Ljava/lang/String;
      43: putfield      #36                 // Field contentFieldName:Ljava/lang/String;
      46: aload_0
      47: aload_1
      48: getfield      #37                 // Field org/springframework/ai/vectorstore/redis/RedisVectorStore$Builder.embeddingFieldName:Ljava/lang/String;
      51: putfield      #40                 // Field embeddingFieldName:Ljava/lang/String;
      54: aload_0
      55: aload_1
      56: getfield      #41                 // Field org/springframework/ai/vectorstore/redis/RedisVectorStore$Builder.vectorAlgorithm:Lorg/springframework/ai/vectorstore/redis/RedisVectorStore$Algorithm;
      59: putfield      #45                 // Field vectorAlgorithm:Lorg/springframework/ai/vectorstore/redis/RedisVectorStore$Algorithm;
      62: aload_0
      63: aload_1
      64: getfield      #46                 // Field org/springframework/ai/vectorstore/redis/RedisVectorStore$Builder.metadataFields:Ljava/util/List;
      67: putfield      #50                 // Field metadataFields:Ljava/util/List;
      70: aload_0
      71: aload_1
      72: getfield      #51                 // Field org/springframework/ai/vectorstore/redis/RedisVectorStore$Builder.initializeSchema:Z
      75: putfield      #55                 // Field initializeSchema:Z
      78: aload_0
      79: new           #56                 // class org/springframework/ai/vectorstore/redis/RedisFilterExpressionConverter
      82: dup
      83: aload_0
      84: getfield      #50                 // Field metadataFields:Ljava/util/List;
      87: invokespecial #58                 // Method org/springframework/ai/vectorstore/redis/RedisFilterExpressionConverter."<init>":(Ljava/util/List;)V
      90: putfield      #61                 // Field filterExpressionConverter:Lorg/springframework/ai/vectorstore/filter/FilterExpressionConverter;
      93: return

  public redis.clients.jedis.JedisPooled getJedis();
    Code:
       0: aload_0
       1: getfield      #21                 // Field jedis:Lredis/clients/jedis/JedisPooled;
       4: areturn

  public void doAdd(java.util.List<org.springframework.ai.document.Document>);
    Code:
       0: aload_0
       1: getfield      #21                 // Field jedis:Lredis/clients/jedis/JedisPooled;
       4: invokevirtual #65                 // Method redis/clients/jedis/JedisPooled.pipelined:()Lredis/clients/jedis/Pipeline;
       7: astore_2
       8: aload_0
       9: getfield      #71                 // Field embeddingModel:Lorg/springframework/ai/embedding/EmbeddingModel;
      12: aload_1
      13: invokestatic  #75                 // InterfaceMethod org/springframework/ai/embedding/EmbeddingOptions.builder:()Lorg/springframework/ai/embedding/EmbeddingOptions$Builder;
      16: invokeinterface #81,  1           // InterfaceMethod org/springframework/ai/embedding/EmbeddingOptions$Builder.build:()Lorg/springframework/ai/embedding/EmbeddingOptions;
      21: aload_0
      22: getfield      #87                 // Field batchingStrategy:Lorg/springframework/ai/embedding/BatchingStrategy;
      25: invokeinterface #91,  4           // InterfaceMethod org/springframework/ai/embedding/EmbeddingModel.embed:(Ljava/util/List;Lorg/springframework/ai/embedding/EmbeddingOptions;Lorg/springframework/ai/embedding/BatchingStrategy;)Ljava/util/List;
      30: astore_3
      31: aload_1
      32: invokeinterface #97,  1           // InterfaceMethod java/util/List.iterator:()Ljava/util/Iterator;
      37: astore        4
      39: aload         4
      41: invokeinterface #103,  1          // InterfaceMethod java/util/Iterator.hasNext:()Z
      46: ifeq          141
      49: aload         4
      51: invokeinterface #109,  1          // InterfaceMethod java/util/Iterator.next:()Ljava/lang/Object;
      56: checkcast     #113                // class org/springframework/ai/document/Document
      59: astore        5
      61: new           #115                // class java/util/HashMap
      64: dup
      65: invokespecial #117                // Method java/util/HashMap."<init>":()V
      68: astore        6
      70: aload         6
      72: aload_0
      73: getfield      #40                 // Field embeddingFieldName:Ljava/lang/String;
      76: aload_3
      77: aload_1
      78: aload         5
      80: invokeinterface #120,  2          // InterfaceMethod java/util/List.indexOf:(Ljava/lang/Object;)I
      85: invokeinterface #124,  2          // InterfaceMethod java/util/List.get:(I)Ljava/lang/Object;
      90: invokevirtual #128                // Method java/util/HashMap.put:(Ljava/lang/Object;Ljava/lang/Object;)Ljava/lang/Object;
      93: pop
      94: aload         6
      96: aload_0
      97: getfield      #36                 // Field contentFieldName:Ljava/lang/String;
     100: aload         5
     102: invokevirtual #132                // Method org/springframework/ai/document/Document.getText:()Ljava/lang/String;
     105: invokevirtual #128                // Method java/util/HashMap.put:(Ljava/lang/Object;Ljava/lang/Object;)Ljava/lang/Object;
     108: pop
     109: aload         6
     111: aload         5
     113: invokevirtual #136                // Method org/springframework/ai/document/Document.getMetadata:()Ljava/util/Map;
     116: invokevirtual #140                // Method java/util/HashMap.putAll:(Ljava/util/Map;)V
     119: aload_2
     120: aload_0
     121: aload         5
     123: invokevirtual #144                // Method org/springframework/ai/document/Document.getId:()Ljava/lang/String;
     126: invokevirtual #147                // Method key:(Ljava/lang/String;)Ljava/lang/String;
     129: getstatic     #151                // Field JSON_SET_PATH:Lredis/clients/jedis/json/Path2;
     132: aload         6
     134: invokevirtual #155                // Method redis/clients/jedis/Pipeline.jsonSetWithEscape:(Ljava/lang/String;Lredis/clients/jedis/json/Path2;Ljava/lang/Object;)Lredis/clients/jedis/Response;
     137: pop
     138: goto          39
     141: aload_2
     142: invokevirtual #161                // Method redis/clients/jedis/Pipeline.syncAndReturnAll:()Ljava/util/List;
     145: astore        4
     147: aload         4
     149: invokeinterface #165,  1          // InterfaceMethod java/util/List.stream:()Ljava/util/stream/Stream;
     154: getstatic     #169                // Field RESPONSE_OK:Ljava/util/function/Predicate;
     157: invokestatic  #173                // InterfaceMethod java/util/function/Predicate.not:(Ljava/util/function/Predicate;)Ljava/util/function/Predicate;
     160: invokeinterface #179,  2          // InterfaceMethod java/util/stream/Stream.filter:(Ljava/util/function/Predicate;)Ljava/util/stream/Stream;
     165: invokeinterface #185,  1          // InterfaceMethod java/util/stream/Stream.findAny:()Ljava/util/Optional;
     170: astore        5
     172: aload         5
     174: invokevirtual #189                // Method java/util/Optional.isPresent:()Z
     177: ifeq          230
     180: ldc           #194                // String Could not add document: {0}
     182: iconst_1
     183: anewarray     #196                // class java/lang/Object
     186: dup
     187: iconst_0
     188: aload         5
     190: invokevirtual #198                // Method java/util/Optional.get:()Ljava/lang/Object;
     193: aastore
     194: invokestatic  #200                // Method java/text/MessageFormat.format:(Ljava/lang/String;[Ljava/lang/Object;)Ljava/lang/String;
     197: astore        6
     199: getstatic     #206                // Field logger:Lorg/slf4j/Logger;
     202: invokeinterface #210,  1          // InterfaceMethod org/slf4j/Logger.isErrorEnabled:()Z
     207: ifeq          220
     210: getstatic     #206                // Field logger:Lorg/slf4j/Logger;
     213: aload         6
     215: invokeinterface #215,  2          // InterfaceMethod org/slf4j/Logger.error:(Ljava/lang/String;)V
     220: new           #219                // class java/lang/RuntimeException
     223: dup
     224: aload         6
     226: invokespecial #221                // Method java/lang/RuntimeException."<init>":(Ljava/lang/String;)V
     229: athrow
     230: aload_2
     231: ifnull        263
     234: aload_2
     235: invokevirtual #223                // Method redis/clients/jedis/Pipeline.close:()V
     238: goto          263
     241: astore_3
     242: aload_2
     243: ifnull        261
     246: aload_2
     247: invokevirtual #223                // Method redis/clients/jedis/Pipeline.close:()V
     250: goto          261
     253: astore        4
     255: aload_3
     256: aload         4
     258: invokevirtual #228                // Method java/lang/Throwable.addSuppressed:(Ljava/lang/Throwable;)V
     261: aload_3
     262: athrow
     263: return
    Exception table:
       from    to  target type
           8   230   241   Class java/lang/Throwable
         246   250   253   Class java/lang/Throwable

  private java.lang.String key(java.lang.String);
    Code:
       0: aload_0
       1: getfield      #32                 // Field prefix:Ljava/lang/String;
       4: aload_1
       5: invokedynamic #232,  0            // InvokeDynamic #0:makeConcatWithConstants:(Ljava/lang/String;Ljava/lang/String;)Ljava/lang/String;
      10: areturn

  public void doDelete(java.util.List<java.lang.String>);
    Code:
       0: aload_0
       1: getfield      #21                 // Field jedis:Lredis/clients/jedis/JedisPooled;
       4: invokevirtual #65                 // Method redis/clients/jedis/JedisPooled.pipelined:()Lredis/clients/jedis/Pipeline;
       7: astore_2
       8: aload_1
       9: invokeinterface #97,  1           // InterfaceMethod java/util/List.iterator:()Ljava/util/Iterator;
      14: astore_3
      15: aload_3
      16: invokeinterface #103,  1          // InterfaceMethod java/util/Iterator.hasNext:()Z
      21: ifeq          49
      24: aload_3
      25: invokeinterface #109,  1          // InterfaceMethod java/util/Iterator.next:()Ljava/lang/Object;
      30: checkcast     #236                // class java/lang/String
      33: astore        4
      35: aload_2
      36: aload_0
      37: aload         4
      39: invokevirtual #147                // Method key:(Ljava/lang/String;)Ljava/lang/String;
      42: invokevirtual #238                // Method redis/clients/jedis/Pipeline.jsonDel:(Ljava/lang/String;)Lredis/clients/jedis/Response;
      45: pop
      46: goto          15
      49: aload_2
      50: invokevirtual #161                // Method redis/clients/jedis/Pipeline.syncAndReturnAll:()Ljava/util/List;
      53: astore_3
      54: aload_3
      55: invokeinterface #165,  1          // InterfaceMethod java/util/List.stream:()Ljava/util/stream/Stream;
      60: getstatic     #242                // Field RESPONSE_DEL_OK:Ljava/util/function/Predicate;
      63: invokestatic  #173                // InterfaceMethod java/util/function/Predicate.not:(Ljava/util/function/Predicate;)Ljava/util/function/Predicate;
      66: invokeinterface #179,  2          // InterfaceMethod java/util/stream/Stream.filter:(Ljava/util/function/Predicate;)Ljava/util/stream/Stream;
      71: invokeinterface #185,  1          // InterfaceMethod java/util/stream/Stream.findAny:()Ljava/util/Optional;
      76: astore        4
      78: aload         4
      80: invokevirtual #189                // Method java/util/Optional.isPresent:()Z
      83: ifeq          112
      86: getstatic     #206                // Field logger:Lorg/slf4j/Logger;
      89: invokeinterface #210,  1          // InterfaceMethod org/slf4j/Logger.isErrorEnabled:()Z
      94: ifeq          112
      97: getstatic     #206                // Field logger:Lorg/slf4j/Logger;
     100: ldc           #245                // String Could not delete document: {}
     102: aload         4
     104: invokevirtual #198                // Method java/util/Optional.get:()Ljava/lang/Object;
     107: invokeinterface #247,  3          // InterfaceMethod org/slf4j/Logger.error:(Ljava/lang/String;Ljava/lang/Object;)V
     112: aload_2
     113: ifnull        145
     116: aload_2
     117: invokevirtual #223                // Method redis/clients/jedis/Pipeline.close:()V
     120: goto          145
     123: astore_3
     124: aload_2
     125: ifnull        143
     128: aload_2
     129: invokevirtual #223                // Method redis/clients/jedis/Pipeline.close:()V
     132: goto          143
     135: astore        4
     137: aload_3
     138: aload         4
     140: invokevirtual #228                // Method java/lang/Throwable.addSuppressed:(Ljava/lang/Throwable;)V
     143: aload_3
     144: athrow
     145: return
    Exception table:
       from    to  target type
           8   112   123   Class java/lang/Throwable
         128   132   135   Class java/lang/Throwable

  protected void doDelete(org.springframework.ai.vectorstore.filter.Filter$Expression);
    Code:
       0: aload_1
       1: ldc           #250                // String Filter expression must not be null
       3: invokestatic  #15                 // Method org/springframework/util/Assert.notNull:(Ljava/lang/Object;Ljava/lang/String;)V
       6: aload_0
       7: getfield      #61                 // Field filterExpressionConverter:Lorg/springframework/ai/vectorstore/filter/FilterExpressionConverter;
      10: aload_1
      11: invokeinterface #252,  2          // InterfaceMethod org/springframework/ai/vectorstore/filter/FilterExpressionConverter.convertExpression:(Lorg/springframework/ai/vectorstore/filter/Filter$Expression;)Ljava/lang/String;
      16: astore_2
      17: new           #258                // class java/util/ArrayList
      20: dup
      21: invokespecial #260                // Method java/util/ArrayList."<init>":()V
      24: astore_3
      25: aload_0
      26: getfield      #21                 // Field jedis:Lredis/clients/jedis/JedisPooled;
      29: aload_0
      30: getfield      #28                 // Field indexName:Ljava/lang/String;
      33: aload_2
      34: invokevirtual #261                // Method redis/clients/jedis/JedisPooled.ftSearch:(Ljava/lang/String;Ljava/lang/String;)Lredis/clients/jedis/search/SearchResult;
      37: astore        4
      39: aload         4
      41: invokevirtual #265                // Method redis/clients/jedis/search/SearchResult.getDocuments:()Ljava/util/List;
      44: invokeinterface #97,  1           // InterfaceMethod java/util/List.iterator:()Ljava/util/Iterator;
      49: astore        5
      51: aload         5
      53: invokeinterface #103,  1          // InterfaceMethod java/util/Iterator.hasNext:()Z
      58: ifeq          105
      61: aload         5
      63: invokeinterface #109,  1          // InterfaceMethod java/util/Iterator.next:()Ljava/lang/Object;
      68: checkcast     #270                // class redis/clients/jedis/search/Document
      71: astore        6
      73: aload         6
      75: invokevirtual #272                // Method redis/clients/jedis/search/Document.getId:()Ljava/lang/String;
      78: astore        7
      80: aload_3
      81: aload         7
      83: aload_0
      84: ldc_w         #273                // String
      87: invokevirtual #147                // Method key:(Ljava/lang/String;)Ljava/lang/String;
      90: ldc_w         #273                // String
      93: invokevirtual #275                // Method java/lang/String.replace:(Ljava/lang/CharSequence;Ljava/lang/CharSequence;)Ljava/lang/String;
      96: invokeinterface #279,  2          // InterfaceMethod java/util/List.add:(Ljava/lang/Object;)Z
     101: pop
     102: goto          51
     105: aload_3
     106: invokeinterface #283,  1          // InterfaceMethod java/util/List.isEmpty:()Z
     111: ifne          294
     114: aload_0
     115: getfield      #21                 // Field jedis:Lredis/clients/jedis/JedisPooled;
     118: invokevirtual #65                 // Method redis/clients/jedis/JedisPooled.pipelined:()Lredis/clients/jedis/Pipeline;
     121: astore        5
     123: aload_3
     124: invokeinterface #97,  1           // InterfaceMethod java/util/List.iterator:()Ljava/util/Iterator;
     129: astore        6
     131: aload         6
     133: invokeinterface #103,  1          // InterfaceMethod java/util/Iterator.hasNext:()Z
     138: ifeq          168
     141: aload         6
     143: invokeinterface #109,  1          // InterfaceMethod java/util/Iterator.next:()Ljava/lang/Object;
     148: checkcast     #236                // class java/lang/String
     151: astore        7
     153: aload         5
     155: aload_0
     156: aload         7
     158: invokevirtual #147                // Method key:(Ljava/lang/String;)Ljava/lang/String;
     161: invokevirtual #238                // Method redis/clients/jedis/Pipeline.jsonDel:(Ljava/lang/String;)Lredis/clients/jedis/Response;
     164: pop
     165: goto          131
     168: aload         5
     170: invokevirtual #161                // Method redis/clients/jedis/Pipeline.syncAndReturnAll:()Ljava/util/List;
     173: astore        6
     175: aload         6
     177: invokeinterface #165,  1          // InterfaceMethod java/util/List.stream:()Ljava/util/stream/Stream;
     182: getstatic     #242                // Field RESPONSE_DEL_OK:Ljava/util/function/Predicate;
     185: invokestatic  #173                // InterfaceMethod java/util/function/Predicate.not:(Ljava/util/function/Predicate;)Ljava/util/function/Predicate;
     188: invokeinterface #179,  2          // InterfaceMethod java/util/stream/Stream.filter:(Ljava/util/function/Predicate;)Ljava/util/stream/Stream;
     193: invokeinterface #185,  1          // InterfaceMethod java/util/stream/Stream.findAny:()Ljava/util/Optional;
     198: astore        7
     200: aload         7
     202: invokevirtual #189                // Method java/util/Optional.isPresent:()Z
     205: ifeq          234
     208: getstatic     #206                // Field logger:Lorg/slf4j/Logger;
     211: ldc           #245                // String Could not delete document: {}
     213: aload         7
     215: invokevirtual #198                // Method java/util/Optional.get:()Ljava/lang/Object;
     218: invokeinterface #247,  3          // InterfaceMethod org/slf4j/Logger.error:(Ljava/lang/String;Ljava/lang/Object;)V
     223: new           #286                // class java/lang/IllegalStateException
     226: dup
     227: ldc_w         #288                // String Failed to delete some documents
     230: invokespecial #290                // Method java/lang/IllegalStateException."<init>":(Ljava/lang/String;)V
     233: athrow
     234: aload         5
     236: ifnull        274
     239: aload         5
     241: invokevirtual #223                // Method redis/clients/jedis/Pipeline.close:()V
     244: goto          274
     247: astore        6
     249: aload         5
     251: ifnull        271
     254: aload         5
     256: invokevirtual #223                // Method redis/clients/jedis/Pipeline.close:()V
     259: goto          271
     262: astore        7
     264: aload         6
     266: aload         7
     268: invokevirtual #228                // Method java/lang/Throwable.addSuppressed:(Ljava/lang/Throwable;)V
     271: aload         6
     273: athrow
     274: getstatic     #206                // Field logger:Lorg/slf4j/Logger;
     277: ldc_w         #291                // String Deleted {} documents matching filter expression
     280: aload_3
     281: invokeinterface #293,  1          // InterfaceMethod java/util/List.size:()I
     286: invokestatic  #297                // Method java/lang/Integer.valueOf:(I)Ljava/lang/Integer;
     289: invokeinterface #303,  3          // InterfaceMethod org/slf4j/Logger.debug:(Ljava/lang/String;Ljava/lang/Object;)V
     294: goto          322
     297: astore_2
     298: getstatic     #206                // Field logger:Lorg/slf4j/Logger;
     301: ldc_w         #308                // String Failed to delete documents by filter
     304: aload_2
     305: invokeinterface #310,  3          // InterfaceMethod org/slf4j/Logger.error:(Ljava/lang/String;Ljava/lang/Throwable;)V
     310: new           #286                // class java/lang/IllegalStateException
     313: dup
     314: ldc_w         #308                // String Failed to delete documents by filter
     317: aload_2
     318: invokespecial #313                // Method java/lang/IllegalStateException."<init>":(Ljava/lang/String;Ljava/lang/Throwable;)V
     321: athrow
     322: return
    Exception table:
       from    to  target type
         123   234   247   Class java/lang/Throwable
         254   259   262   Class java/lang/Throwable
           6   294   297   Class java/lang/Exception

  public java.util.List<org.springframework.ai.document.Document> doSimilaritySearch(org.springframework.ai.vectorstore.SearchRequest);
    Code:
       0: aload_1
       1: invokevirtual #315                // Method org/springframework/ai/vectorstore/SearchRequest.getTopK:()I
       4: ifle          11
       7: iconst_1
       8: goto          12
      11: iconst_0
      12: ldc_w         #320                // String The number of documents to be returned must be greater than zero
      15: invokestatic  #322                // Method org/springframework/util/Assert.isTrue:(ZLjava/lang/String;)V
      18: aload_1
      19: invokevirtual #326                // Method org/springframework/ai/vectorstore/SearchRequest.getSimilarityThreshold:()D
      22: dconst_0
      23: dcmpl
      24: iflt          40
      27: aload_1
      28: invokevirtual #326                // Method org/springframework/ai/vectorstore/SearchRequest.getSimilarityThreshold:()D
      31: dconst_1
      32: dcmpg
      33: ifgt          40
      36: iconst_1
      37: goto          41
      40: iconst_0
      41: ldc_w         #330                // String The similarity score is bounded between 0 and 1; least to most similar respectively.
      44: invokestatic  #322                // Method org/springframework/util/Assert.isTrue:(ZLjava/lang/String;)V
      47: aload_0
      48: aload_1
      49: invokevirtual #332                // Method nativeExpressionFilter:(Lorg/springframework/ai/vectorstore/SearchRequest;)Ljava/lang/String;
      52: astore_2
      53: ldc_w         #336                // String %s=>[KNN %s @%s $%s AS %s]
      56: iconst_5
      57: anewarray     #196                // class java/lang/Object
      60: dup
      61: iconst_0
      62: aload_2
      63: aastore
      64: dup
      65: iconst_1
      66: aload_1
      67: invokevirtual #315                // Method org/springframework/ai/vectorstore/SearchRequest.getTopK:()I
      70: invokestatic  #297                // Method java/lang/Integer.valueOf:(I)Ljava/lang/Integer;
      73: aastore
      74: dup
      75: iconst_2
      76: aload_0
      77: getfield      #40                 // Field embeddingFieldName:Ljava/lang/String;
      80: aastore
      81: dup
      82: iconst_3
      83: ldc_w         #338                // String BLOB
      86: aastore
      87: dup
      88: iconst_4
      89: ldc_w         #340                // String vector_score
      92: aastore
      93: invokestatic  #342                // Method java/lang/String.format:(Ljava/lang/String;[Ljava/lang/Object;)Ljava/lang/String;
      96: astore_3
      97: new           #258                // class java/util/ArrayList
     100: dup
     101: invokespecial #260                // Method java/util/ArrayList."<init>":()V
     104: astore        4
     106: aload_0
     107: getfield      #50                 // Field metadataFields:Ljava/util/List;
     110: invokeinterface #165,  1          // InterfaceMethod java/util/List.stream:()Ljava/util/stream/Stream;
     115: invokedynamic #343,  0            // InvokeDynamic #1:apply:()Ljava/util/function/Function;
     120: invokeinterface #347,  2          // InterfaceMethod java/util/stream/Stream.map:(Ljava/util/function/Function;)Ljava/util/stream/Stream;
     125: aload         4
     127: dup
     128: invokestatic  #351                // Method java/util/Objects.requireNonNull:(Ljava/lang/Object;)Ljava/lang/Object;
     131: pop
     132: invokedynamic #357,  0            // InvokeDynamic #2:accept:(Ljava/util/List;)Ljava/util/function/Consumer;
     137: invokeinterface #361,  2          // InterfaceMethod java/util/stream/Stream.forEach:(Ljava/util/function/Consumer;)V
     142: aload         4
     144: aload_0
     145: getfield      #40                 // Field embeddingFieldName:Ljava/lang/String;
     148: invokeinterface #279,  2          // InterfaceMethod java/util/List.add:(Ljava/lang/Object;)Z
     153: pop
     154: aload         4
     156: aload_0
     157: getfield      #36                 // Field contentFieldName:Ljava/lang/String;
     160: invokeinterface #279,  2          // InterfaceMethod java/util/List.add:(Ljava/lang/Object;)Z
     165: pop
     166: aload         4
     168: ldc_w         #340                // String vector_score
     171: invokeinterface #279,  2          // InterfaceMethod java/util/List.add:(Ljava/lang/Object;)Z
     176: pop
     177: aload_0
     178: getfield      #71                 // Field embeddingModel:Lorg/springframework/ai/embedding/EmbeddingModel;
     181: aload_1
     182: invokevirtual #365                // Method org/springframework/ai/vectorstore/SearchRequest.getQuery:()Ljava/lang/String;
     185: invokeinterface #368,  2          // InterfaceMethod org/springframework/ai/embedding/EmbeddingModel.embed:(Ljava/lang/String;)[F
     190: astore        5
     192: new           #371                // class redis/clients/jedis/search/Query
     195: dup
     196: aload_3
     197: invokespecial #373                // Method redis/clients/jedis/search/Query."<init>":(Ljava/lang/String;)V
     200: ldc_w         #338                // String BLOB
     203: aload         5
     205: invokestatic  #374                // Method redis/clients/jedis/search/RediSearchUtil.toByteArray:([F)[B
     208: invokevirtual #380                // Method redis/clients/jedis/search/Query.addParam:(Ljava/lang/String;Ljava/lang/Object;)Lredis/clients/jedis/search/Query;
     211: aload         4
     213: iconst_0
     214: anewarray     #236                // class java/lang/String
     217: invokeinterface #384,  2          // InterfaceMethod java/util/List.toArray:([Ljava/lang/Object;)[Ljava/lang/Object;
     222: checkcast     #388                // class "[Ljava/lang/String;"
     225: invokevirtual #390                // Method redis/clients/jedis/search/Query.returnFields:([Ljava/lang/String;)Lredis/clients/jedis/search/Query;
     228: ldc_w         #340                // String vector_score
     231: iconst_1
     232: invokevirtual #394                // Method redis/clients/jedis/search/Query.setSortBy:(Ljava/lang/String;Z)Lredis/clients/jedis/search/Query;
     235: iconst_0
     236: invokestatic  #297                // Method java/lang/Integer.valueOf:(I)Ljava/lang/Integer;
     239: aload_1
     240: invokevirtual #315                // Method org/springframework/ai/vectorstore/SearchRequest.getTopK:()I
     243: invokestatic  #297                // Method java/lang/Integer.valueOf:(I)Ljava/lang/Integer;
     246: invokevirtual #398                // Method redis/clients/jedis/search/Query.limit:(Ljava/lang/Integer;Ljava/lang/Integer;)Lredis/clients/jedis/search/Query;
     249: iconst_2
     250: invokevirtual #402                // Method redis/clients/jedis/search/Query.dialect:(I)Lredis/clients/jedis/search/Query;
     253: astore        6
     255: aload_0
     256: getfield      #21                 // Field jedis:Lredis/clients/jedis/JedisPooled;
     259: aload_0
     260: getfield      #28                 // Field indexName:Ljava/lang/String;
     263: aload         6
     265: invokevirtual #406                // Method redis/clients/jedis/JedisPooled.ftSearch:(Ljava/lang/String;Lredis/clients/jedis/search/Query;)Lredis/clients/jedis/search/SearchResult;
     268: astore        7
     270: aload         7
     272: invokevirtual #265                // Method redis/clients/jedis/search/SearchResult.getDocuments:()Ljava/util/List;
     275: invokeinterface #165,  1          // InterfaceMethod java/util/List.stream:()Ljava/util/stream/Stream;
     280: aload_0
     281: aload_1
     282: invokedynamic #409,  0            // InvokeDynamic #3:test:(Lorg/springframework/ai/vectorstore/redis/RedisVectorStore;Lorg/springframework/ai/vectorstore/SearchRequest;)Ljava/util/function/Predicate;
     287: invokeinterface #179,  2          // InterfaceMethod java/util/stream/Stream.filter:(Ljava/util/function/Predicate;)Ljava/util/stream/Stream;
     292: aload_0
     293: invokedynamic #413,  0            // InvokeDynamic #4:apply:(Lorg/springframework/ai/vectorstore/redis/RedisVectorStore;)Ljava/util/function/Function;
     298: invokeinterface #347,  2          // InterfaceMethod java/util/stream/Stream.map:(Ljava/util/function/Function;)Ljava/util/stream/Stream;
     303: invokeinterface #416,  1          // InterfaceMethod java/util/stream/Stream.toList:()Ljava/util/List;
     308: areturn

  private org.springframework.ai.document.Document toDocument(redis.clients.jedis.search.Document);
    Code:
       0: aload_1
       1: invokevirtual #272                // Method redis/clients/jedis/search/Document.getId:()Ljava/lang/String;
       4: aload_0
       5: getfield      #32                 // Field prefix:Ljava/lang/String;
       8: invokevirtual #419                // Method java/lang/String.length:()I
      11: invokevirtual #422                // Method java/lang/String.substring:(I)Ljava/lang/String;
      14: astore_2
      15: aload_1
      16: aload_0
      17: getfield      #36                 // Field contentFieldName:Ljava/lang/String;
      20: invokevirtual #426                // Method redis/clients/jedis/search/Document.hasProperty:(Ljava/lang/String;)Z
      23: ifeq          37
      26: aload_1
      27: aload_0
      28: getfield      #36                 // Field contentFieldName:Ljava/lang/String;
      31: invokevirtual #430                // Method redis/clients/jedis/search/Document.getString:(Ljava/lang/String;)Ljava/lang/String;
      34: goto          40
      37: ldc_w         #273                // String
      40: astore_3
      41: aload_0
      42: getfield      #50                 // Field metadataFields:Ljava/util/List;
      45: invokeinterface #165,  1          // InterfaceMethod java/util/List.stream:()Ljava/util/stream/Stream;
      50: invokedynamic #343,  0            // InvokeDynamic #1:apply:()Ljava/util/function/Function;
      55: invokeinterface #347,  2          // InterfaceMethod java/util/stream/Stream.map:(Ljava/util/function/Function;)Ljava/util/stream/Stream;
      60: aload_1
      61: dup
      62: invokestatic  #351                // Method java/util/Objects.requireNonNull:(Ljava/lang/Object;)Ljava/lang/Object;
      65: pop
      66: invokedynamic #433,  0            // InvokeDynamic #5:test:(Lredis/clients/jedis/search/Document;)Ljava/util/function/Predicate;
      71: invokeinterface #179,  2          // InterfaceMethod java/util/stream/Stream.filter:(Ljava/util/function/Predicate;)Ljava/util/stream/Stream;
      76: invokestatic  #436                // InterfaceMethod java/util/function/Function.identity:()Ljava/util/function/Function;
      79: aload_1
      80: dup
      81: invokestatic  #351                // Method java/util/Objects.requireNonNull:(Ljava/lang/Object;)Ljava/lang/Object;
      84: pop
      85: invokedynamic #441,  0            // InvokeDynamic #6:apply:(Lredis/clients/jedis/search/Document;)Ljava/util/function/Function;
      90: invokestatic  #444                // Method java/util/stream/Collectors.toMap:(Ljava/util/function/Function;Ljava/util/function/Function;)Ljava/util/stream/Collector;
      93: invokeinterface #450,  2          // InterfaceMethod java/util/stream/Stream.collect:(Ljava/util/stream/Collector;)Ljava/lang/Object;
      98: checkcast     #454                // class java/util/Map
     101: astore        4
     103: aload         4
     105: ldc_w         #340                // String vector_score
     108: fconst_1
     109: aload_0
     110: aload_1
     111: invokevirtual #456                // Method similarityScore:(Lredis/clients/jedis/search/Document;)F
     114: fsub
     115: invokestatic  #460                // Method java/lang/Float.valueOf:(F)Ljava/lang/Float;
     118: invokeinterface #465,  3          // InterfaceMethod java/util/Map.put:(Ljava/lang/Object;Ljava/lang/Object;)Ljava/lang/Object;
     123: pop
     124: aload         4
     126: getstatic     #466                // Field org/springframework/ai/document/DocumentMetadata.DISTANCE:Lorg/springframework/ai/document/DocumentMetadata;
     129: invokevirtual #472                // Method org/springframework/ai/document/DocumentMetadata.value:()Ljava/lang/String;
     132: fconst_1
     133: aload_0
     134: aload_1
     135: invokevirtual #456                // Method similarityScore:(Lredis/clients/jedis/search/Document;)F
     138: fsub
     139: invokestatic  #460                // Method java/lang/Float.valueOf:(F)Ljava/lang/Float;
     142: invokeinterface #465,  3          // InterfaceMethod java/util/Map.put:(Ljava/lang/Object;Ljava/lang/Object;)Ljava/lang/Object;
     147: pop
     148: invokestatic  #475                // Method org/springframework/ai/document/Document.builder:()Lorg/springframework/ai/document/Document$Builder;
     151: aload_2
     152: invokevirtual #478                // Method org/springframework/ai/document/Document$Builder.id:(Ljava/lang/String;)Lorg/springframework/ai/document/Document$Builder;
     155: aload_3
     156: invokevirtual #484                // Method org/springframework/ai/document/Document$Builder.text:(Ljava/lang/String;)Lorg/springframework/ai/document/Document$Builder;
     159: aload         4
     161: invokevirtual #487                // Method org/springframework/ai/document/Document$Builder.metadata:(Ljava/util/Map;)Lorg/springframework/ai/document/Document$Builder;
     164: aload_0
     165: aload_1
     166: invokevirtual #456                // Method similarityScore:(Lredis/clients/jedis/search/Document;)F
     169: f2d
     170: invokestatic  #491                // Method java/lang/Double.valueOf:(D)Ljava/lang/Double;
     173: invokevirtual #496                // Method org/springframework/ai/document/Document$Builder.score:(Ljava/lang/Double;)Lorg/springframework/ai/document/Document$Builder;
     176: invokevirtual #500                // Method org/springframework/ai/document/Document$Builder.build:()Lorg/springframework/ai/document/Document;
     179: areturn

  private float similarityScore(redis.clients.jedis.search.Document);
    Code:
       0: fconst_2
       1: aload_1
       2: ldc_w         #340                // String vector_score
       5: invokevirtual #430                // Method redis/clients/jedis/search/Document.getString:(Ljava/lang/String;)Ljava/lang/String;
       8: invokestatic  #503                // Method java/lang/Float.parseFloat:(Ljava/lang/String;)F
      11: fsub
      12: fconst_2
      13: fdiv
      14: freturn

  private java.lang.String nativeExpressionFilter(org.springframework.ai.vectorstore.SearchRequest);
    Code:
       0: aload_1
       1: invokevirtual #507                // Method org/springframework/ai/vectorstore/SearchRequest.getFilterExpression:()Lorg/springframework/ai/vectorstore/filter/Filter$Expression;
       4: ifnonnull     11
       7: ldc_w         #511                // String *
      10: areturn
      11: aload_0
      12: getfield      #61                 // Field filterExpressionConverter:Lorg/springframework/ai/vectorstore/filter/FilterExpressionConverter;
      15: aload_1
      16: invokevirtual #507                // Method org/springframework/ai/vectorstore/SearchRequest.getFilterExpression:()Lorg/springframework/ai/vectorstore/filter/Filter$Expression;
      19: invokeinterface #252,  2          // InterfaceMethod org/springframework/ai/vectorstore/filter/FilterExpressionConverter.convertExpression:(Lorg/springframework/ai/vectorstore/filter/Filter$Expression;)Ljava/lang/String;
      24: invokedynamic #513,  0            // InvokeDynamic #7:makeConcatWithConstants:(Ljava/lang/String;)Ljava/lang/String;
      29: areturn

  public void afterPropertiesSet();
    Code:
       0: aload_0
       1: getfield      #55                 // Field initializeSchema:Z
       4: ifne          8
       7: return
       8: aload_0
       9: getfield      #21                 // Field jedis:Lredis/clients/jedis/JedisPooled;
      12: invokevirtual #515                // Method redis/clients/jedis/JedisPooled.ftList:()Ljava/util/Set;
      15: aload_0
      16: getfield      #28                 // Field indexName:Ljava/lang/String;
      19: invokeinterface #519,  2          // InterfaceMethod java/util/Set.contains:(Ljava/lang/Object;)Z
      24: ifeq          28
      27: return
      28: aload_0
      29: getfield      #21                 // Field jedis:Lredis/clients/jedis/JedisPooled;
      32: aload_0
      33: getfield      #28                 // Field indexName:Ljava/lang/String;
      36: invokestatic  #524                // Method redis/clients/jedis/search/FTCreateParams.createParams:()Lredis/clients/jedis/search/FTCreateParams;
      39: getstatic     #530                // Field redis/clients/jedis/search/IndexDataType.JSON:Lredis/clients/jedis/search/IndexDataType;
      42: invokevirtual #536                // Method redis/clients/jedis/search/FTCreateParams.on:(Lredis/clients/jedis/search/IndexDataType;)Lredis/clients/jedis/search/FTCreateParams;
      45: aload_0
      46: getfield      #32                 // Field prefix:Ljava/lang/String;
      49: invokevirtual #540                // Method redis/clients/jedis/search/FTCreateParams.addPrefix:(Ljava/lang/String;)Lredis/clients/jedis/search/FTCreateParams;
      52: aload_0
      53: invokevirtual #544                // Method schemaFields:()Ljava/lang/Iterable;
      56: invokevirtual #548                // Method redis/clients/jedis/JedisPooled.ftCreate:(Ljava/lang/String;Lredis/clients/jedis/search/FTCreateParams;Ljava/lang/Iterable;)Ljava/lang/String;
      59: astore_1
      60: getstatic     #169                // Field RESPONSE_OK:Ljava/util/function/Predicate;
      63: aload_1
      64: invokeinterface #552,  2          // InterfaceMethod java/util/function/Predicate.test:(Ljava/lang/Object;)Z
      69: ifne          96
      72: ldc_w         #554                // String Could not create index: {0}
      75: iconst_1
      76: anewarray     #196                // class java/lang/Object
      79: dup
      80: iconst_0
      81: aload_1
      82: aastore
      83: invokestatic  #200                // Method java/text/MessageFormat.format:(Ljava/lang/String;[Ljava/lang/Object;)Ljava/lang/String;
      86: astore_2
      87: new           #219                // class java/lang/RuntimeException
      90: dup
      91: aload_2
      92: invokespecial #221                // Method java/lang/RuntimeException."<init>":(Ljava/lang/String;)V
      95: athrow
      96: return

  private java.lang.Iterable<redis.clients.jedis.search.schemafields.SchemaField> schemaFields();
    Code:
       0: new           #115                // class java/util/HashMap
       3: dup
       4: invokespecial #117                // Method java/util/HashMap."<init>":()V
       7: astore_1
       8: aload_1
       9: ldc_w         #556                // String DIM
      12: aload_0
      13: getfield      #71                 // Field embeddingModel:Lorg/springframework/ai/embedding/EmbeddingModel;
      16: invokeinterface #558,  1          // InterfaceMethod org/springframework/ai/embedding/EmbeddingModel.dimensions:()I
      21: invokestatic  #297                // Method java/lang/Integer.valueOf:(I)Ljava/lang/Integer;
      24: invokeinterface #465,  3          // InterfaceMethod java/util/Map.put:(Ljava/lang/Object;Ljava/lang/Object;)Ljava/lang/Object;
      29: pop
      30: aload_1
      31: ldc_w         #561                // String DISTANCE_METRIC
      34: ldc_w         #563                // String COSINE
      37: invokeinterface #465,  3          // InterfaceMethod java/util/Map.put:(Ljava/lang/Object;Ljava/lang/Object;)Ljava/lang/Object;
      42: pop
      43: aload_1
      44: ldc_w         #565                // String TYPE
      47: ldc_w         #567                // String FLOAT32
      50: invokeinterface #465,  3          // InterfaceMethod java/util/Map.put:(Ljava/lang/Object;Ljava/lang/Object;)Ljava/lang/Object;
      55: pop
      56: new           #258                // class java/util/ArrayList
      59: dup
      60: invokespecial #260                // Method java/util/ArrayList."<init>":()V
      63: astore_2
      64: aload_2
      65: aload_0
      66: aload_0
      67: getfield      #36                 // Field contentFieldName:Ljava/lang/String;
      70: invokevirtual #569                // Method jsonPath:(Ljava/lang/String;)Ljava/lang/String;
      73: invokestatic  #572                // Method redis/clients/jedis/search/schemafields/TextField.of:(Ljava/lang/String;)Lredis/clients/jedis/search/schemafields/TextField;
      76: aload_0
      77: getfield      #36                 // Field contentFieldName:Ljava/lang/String;
      80: invokevirtual #578                // Method redis/clients/jedis/search/schemafields/TextField.as:(Ljava/lang/String;)Lredis/clients/jedis/search/schemafields/TextField;
      83: dconst_1
      84: invokevirtual #581                // Method redis/clients/jedis/search/schemafields/TextField.weight:(D)Lredis/clients/jedis/search/schemafields/TextField;
      87: invokeinterface #279,  2          // InterfaceMethod java/util/List.add:(Ljava/lang/Object;)Z
      92: pop
      93: aload_2
      94: invokestatic  #585                // Method redis/clients/jedis/search/schemafields/VectorField.builder:()Lredis/clients/jedis/search/schemafields/VectorField$Builder;
      97: aload_0
      98: aload_0
      99: getfield      #40                 // Field embeddingFieldName:Ljava/lang/String;
     102: invokevirtual #569                // Method jsonPath:(Ljava/lang/String;)Ljava/lang/String;
     105: invokevirtual #590                // Method redis/clients/jedis/search/schemafields/VectorField$Builder.fieldName:(Ljava/lang/String;)Lredis/clients/jedis/search/schemafields/VectorField$Builder;
     108: aload_0
     109: invokevirtual #596                // Method vectorAlgorithm:()Lredis/clients/jedis/search/schemafields/VectorField$VectorAlgorithm;
     112: invokevirtual #599                // Method redis/clients/jedis/search/schemafields/VectorField$Builder.algorithm:(Lredis/clients/jedis/search/schemafields/VectorField$VectorAlgorithm;)Lredis/clients/jedis/search/schemafields/VectorField$Builder;
     115: aload_1
     116: invokevirtual #603                // Method redis/clients/jedis/search/schemafields/VectorField$Builder.attributes:(Ljava/util/Map;)Lredis/clients/jedis/search/schemafields/VectorField$Builder;
     119: aload_0
     120: getfield      #40                 // Field embeddingFieldName:Ljava/lang/String;
     123: invokevirtual #607                // Method redis/clients/jedis/search/schemafields/VectorField$Builder.as:(Ljava/lang/String;)Lredis/clients/jedis/search/schemafields/VectorField$Builder;
     126: invokevirtual #609                // Method redis/clients/jedis/search/schemafields/VectorField$Builder.build:()Lredis/clients/jedis/search/schemafields/VectorField;
     129: invokeinterface #279,  2          // InterfaceMethod java/util/List.add:(Ljava/lang/Object;)Z
     134: pop
     135: aload_0
     136: getfield      #50                 // Field metadataFields:Ljava/util/List;
     139: invokestatic  #612                // Method org/springframework/util/CollectionUtils.isEmpty:(Ljava/util/Collection;)Z
     142: ifne          191
     145: aload_0
     146: getfield      #50                 // Field metadataFields:Ljava/util/List;
     149: invokeinterface #97,  1           // InterfaceMethod java/util/List.iterator:()Ljava/util/Iterator;
     154: astore_3
     155: aload_3
     156: invokeinterface #103,  1          // InterfaceMethod java/util/Iterator.hasNext:()Z
     161: ifeq          191
     164: aload_3
     165: invokeinterface #109,  1          // InterfaceMethod java/util/Iterator.next:()Ljava/lang/Object;
     170: checkcast     #617                // class org/springframework/ai/vectorstore/redis/RedisVectorStore$MetadataField
     173: astore        4
     175: aload_2
     176: aload_0
     177: aload         4
     179: invokevirtual #619                // Method schemaField:(Lorg/springframework/ai/vectorstore/redis/RedisVectorStore$MetadataField;)Lredis/clients/jedis/search/schemafields/SchemaField;
     182: invokeinterface #279,  2          // InterfaceMethod java/util/List.add:(Ljava/lang/Object;)Z
     187: pop
     188: goto          155
     191: aload_2
     192: areturn

  private redis.clients.jedis.search.schemafields.SchemaField schemaField(org.springframework.ai.vectorstore.redis.RedisVectorStore$MetadataField);
    Code:
       0: aload_0
       1: aload_1
       2: getfield      #623                // Field org/springframework/ai/vectorstore/redis/RedisVectorStore$MetadataField.name:Ljava/lang/String;
       5: invokevirtual #569                // Method jsonPath:(Ljava/lang/String;)Ljava/lang/String;
       8: astore_2
       9: getstatic     #626                // Field org/springframework/ai/vectorstore/redis/RedisVectorStore$1.$SwitchMap$redis$clients$jedis$search$Schema$FieldType:[I
      12: aload_1
      13: getfield      #632                // Field org/springframework/ai/vectorstore/redis/RedisVectorStore$MetadataField.fieldType:Lredis/clients/jedis/search/Schema$FieldType;
      16: invokevirtual #636                // Method redis/clients/jedis/search/Schema$FieldType.ordinal:()I
      19: iaload
      20: tableswitch   { // 1 to 3

                     1: 48

                     2: 62

                     3: 76
               default: 90
          }
      48: aload_2
      49: invokestatic  #641                // Method redis/clients/jedis/search/schemafields/NumericField.of:(Ljava/lang/String;)Lredis/clients/jedis/search/schemafields/NumericField;
      52: aload_1
      53: getfield      #623                // Field org/springframework/ai/vectorstore/redis/RedisVectorStore$MetadataField.name:Ljava/lang/String;
      56: invokevirtual #646                // Method redis/clients/jedis/search/schemafields/NumericField.as:(Ljava/lang/String;)Lredis/clients/jedis/search/schemafields/NumericField;
      59: goto          122
      62: aload_2
      63: invokestatic  #648                // Method redis/clients/jedis/search/schemafields/TagField.of:(Ljava/lang/String;)Lredis/clients/jedis/search/schemafields/TagField;
      66: aload_1
      67: getfield      #623                // Field org/springframework/ai/vectorstore/redis/RedisVectorStore$MetadataField.name:Ljava/lang/String;
      70: invokevirtual #653                // Method redis/clients/jedis/search/schemafields/TagField.as:(Ljava/lang/String;)Lredis/clients/jedis/search/schemafields/TagField;
      73: goto          122
      76: aload_2
      77: invokestatic  #572                // Method redis/clients/jedis/search/schemafields/TextField.of:(Ljava/lang/String;)Lredis/clients/jedis/search/schemafields/TextField;
      80: aload_1
      81: getfield      #623                // Field org/springframework/ai/vectorstore/redis/RedisVectorStore$MetadataField.name:Ljava/lang/String;
      84: invokevirtual #578                // Method redis/clients/jedis/search/schemafields/TextField.as:(Ljava/lang/String;)Lredis/clients/jedis/search/schemafields/TextField;
      87: goto          122
      90: new           #655                // class java/lang/IllegalArgumentException
      93: dup
      94: ldc_w         #657                // String Field {0} has unsupported type {1}
      97: iconst_2
      98: anewarray     #196                // class java/lang/Object
     101: dup
     102: iconst_0
     103: aload_1
     104: getfield      #623                // Field org/springframework/ai/vectorstore/redis/RedisVectorStore$MetadataField.name:Ljava/lang/String;
     107: aastore
     108: dup
     109: iconst_1
     110: aload_1
     111: getfield      #632                // Field org/springframework/ai/vectorstore/redis/RedisVectorStore$MetadataField.fieldType:Lredis/clients/jedis/search/Schema$FieldType;
     114: aastore
     115: invokestatic  #200                // Method java/text/MessageFormat.format:(Ljava/lang/String;[Ljava/lang/Object;)Ljava/lang/String;
     118: invokespecial #659                // Method java/lang/IllegalArgumentException."<init>":(Ljava/lang/String;)V
     121: athrow
     122: areturn

  private redis.clients.jedis.search.schemafields.VectorField$VectorAlgorithm vectorAlgorithm();
    Code:
       0: aload_0
       1: getfield      #45                 // Field vectorAlgorithm:Lorg/springframework/ai/vectorstore/redis/RedisVectorStore$Algorithm;
       4: getstatic     #660                // Field org/springframework/ai/vectorstore/redis/RedisVectorStore$Algorithm.HNSW:Lorg/springframework/ai/vectorstore/redis/RedisVectorStore$Algorithm;
       7: if_acmpne     14
      10: getstatic     #665                // Field redis/clients/jedis/search/schemafields/VectorField$VectorAlgorithm.HNSW:Lredis/clients/jedis/search/schemafields/VectorField$VectorAlgorithm;
      13: areturn
      14: getstatic     #670                // Field redis/clients/jedis/search/schemafields/VectorField$VectorAlgorithm.FLAT:Lredis/clients/jedis/search/schemafields/VectorField$VectorAlgorithm;
      17: areturn

  private java.lang.String jsonPath(java.lang.String);
    Code:
       0: aload_1
       1: invokedynamic #673,  0            // InvokeDynamic #8:makeConcatWithConstants:(Ljava/lang/String;)Ljava/lang/String;
       6: areturn

  public org.springframework.ai.vectorstore.observation.VectorStoreObservationContext$Builder createObservationContextBuilder(java.lang.String);
    Code:
       0: getstatic     #674                // Field org/springframework/ai/observation/conventions/VectorStoreProvider.REDIS:Lorg/springframework/ai/observation/conventions/VectorStoreProvider;
       3: invokevirtual #680                // Method org/springframework/ai/observation/conventions/VectorStoreProvider.value:()Ljava/lang/String;
       6: aload_1
       7: invokestatic  #681                // Method org/springframework/ai/vectorstore/observation/VectorStoreObservationContext.builder:(Ljava/lang/String;Ljava/lang/String;)Lorg/springframework/ai/vectorstore/observation/VectorStoreObservationContext$Builder;
      10: aload_0
      11: getfield      #28                 // Field indexName:Ljava/lang/String;
      14: invokevirtual #686                // Method org/springframework/ai/vectorstore/observation/VectorStoreObservationContext$Builder.collectionName:(Ljava/lang/String;)Lorg/springframework/ai/vectorstore/observation/VectorStoreObservationContext$Builder;
      17: aload_0
      18: getfield      #71                 // Field embeddingModel:Lorg/springframework/ai/embedding/EmbeddingModel;
      21: invokeinterface #558,  1          // InterfaceMethod org/springframework/ai/embedding/EmbeddingModel.dimensions:()I
      26: invokestatic  #297                // Method java/lang/Integer.valueOf:(I)Ljava/lang/Integer;
      29: invokevirtual #692                // Method org/springframework/ai/vectorstore/observation/VectorStoreObservationContext$Builder.dimensions:(Ljava/lang/Integer;)Lorg/springframework/ai/vectorstore/observation/VectorStoreObservationContext$Builder;
      32: aload_0
      33: getfield      #40                 // Field embeddingFieldName:Ljava/lang/String;
      36: invokevirtual #695                // Method org/springframework/ai/vectorstore/observation/VectorStoreObservationContext$Builder.fieldName:(Ljava/lang/String;)Lorg/springframework/ai/vectorstore/observation/VectorStoreObservationContext$Builder;
      39: getstatic     #697                // Field org/springframework/ai/observation/conventions/VectorStoreSimilarityMetric.COSINE:Lorg/springframework/ai/observation/conventions/VectorStoreSimilarityMetric;
      42: invokevirtual #702                // Method org/springframework/ai/observation/conventions/VectorStoreSimilarityMetric.value:()Ljava/lang/String;
      45: invokevirtual #703                // Method org/springframework/ai/vectorstore/observation/VectorStoreObservationContext$Builder.similarityMetric:(Ljava/lang/String;)Lorg/springframework/ai/vectorstore/observation/VectorStoreObservationContext$Builder;
      48: areturn

  public <T> java.util.Optional<T> getNativeClient();
    Code:
       0: aload_0
       1: getfield      #21                 // Field jedis:Lredis/clients/jedis/JedisPooled;
       4: astore_1
       5: aload_1
       6: invokestatic  #706                // Method java/util/Optional.of:(Ljava/lang/Object;)Ljava/util/Optional;
       9: areturn

  public static org.springframework.ai.vectorstore.redis.RedisVectorStore$Builder builder(redis.clients.jedis.JedisPooled, org.springframework.ai.embedding.EmbeddingModel);
    Code:
       0: new           #8                  // class org/springframework/ai/vectorstore/redis/RedisVectorStore$Builder
       3: dup
       4: aload_0
       5: aload_1
       6: invokespecial #709                // Method org/springframework/ai/vectorstore/redis/RedisVectorStore$Builder."<init>":(Lredis/clients/jedis/JedisPooled;Lorg/springframework/ai/embedding/EmbeddingModel;)V
       9: areturn

  private boolean lambda$doSimilaritySearch$0(org.springframework.ai.vectorstore.SearchRequest, redis.clients.jedis.search.Document);
    Code:
       0: aload_0
       1: aload_2
       2: invokevirtual #456                // Method similarityScore:(Lredis/clients/jedis/search/Document;)F
       5: f2d
       6: aload_1
       7: invokevirtual #326                // Method org/springframework/ai/vectorstore/SearchRequest.getSimilarityThreshold:()D
      10: dcmpl
      11: iflt          18
      14: iconst_1
      15: goto          19
      18: iconst_0
      19: ireturn

  static {};
    Code:
       0: getstatic     #660                // Field org/springframework/ai/vectorstore/redis/RedisVectorStore$Algorithm.HNSW:Lorg/springframework/ai/vectorstore/redis/RedisVectorStore$Algorithm;
       3: putstatic     #712                // Field DEFAULT_VECTOR_ALGORITHM:Lorg/springframework/ai/vectorstore/redis/RedisVectorStore$Algorithm;
       6: ldc_w         #715                // String $
       9: invokestatic  #717                // Method redis/clients/jedis/json/Path2.of:(Ljava/lang/String;)Lredis/clients/jedis/json/Path2;
      12: putstatic     #151                // Field JSON_SET_PATH:Lredis/clients/jedis/json/Path2;
      15: ldc           #22                 // class org/springframework/ai/vectorstore/redis/RedisVectorStore
      17: invokestatic  #722                // Method org/slf4j/LoggerFactory.getLogger:(Ljava/lang/Class;)Lorg/slf4j/Logger;
      20: putstatic     #206                // Field logger:Lorg/slf4j/Logger;
      23: ldc_w         #728                // String OK
      26: invokestatic  #730                // InterfaceMethod java/util/function/Predicate.isEqual:(Ljava/lang/Object;)Ljava/util/function/Predicate;
      29: putstatic     #169                // Field RESPONSE_OK:Ljava/util/function/Predicate;
      32: lconst_1
      33: invokestatic  #734                // Method java/lang/Long.valueOf:(J)Ljava/lang/Long;
      36: invokestatic  #730                // InterfaceMethod java/util/function/Predicate.isEqual:(Ljava/lang/Object;)Ljava/util/function/Predicate;
      39: putstatic     #242                // Field RESPONSE_DEL_OK:Ljava/util/function/Predicate;
      42: return
}
